<annotation>
	<folder>images</folder>
	<filename>70.jpg</filename>
	<path>C:\Users\Server\PycharmProjects\yolov5\dataset\images\70.jpg</path>
	<source>
		<database>Unknown</database>
	</source>
	<size>
		<width>640</width>
		<height>480</height>
		<depth>3</depth>
	</size>
	<segmented>0</segmented>
	<object>
		<name>Phase1_screw_missing</name>
		<pose>Unspecified</pose>
		<truncated>0</truncated>
		<difficult>0</difficult>
		<bndbox>
			<xmin>224</xmin>
			<ymin>140</ymin>
			<xmax>298</xmax>
			<ymax>204</ymax>
		</bndbox>
	</object>
	<object>
		<name>Phase1_screw_missing</name>
		<pose>Unspecified</pose>
		<truncated>0</truncated>
		<difficult>0</difficult>
		<bndbox>
			<xmin>230</xmin>
			<ymin>279</ymin>
			<xmax>295</xmax>
			<ymax>347</ymax>
		</bndbox>
	</object>
	<object>
		<name>Phase1_screw_missing</name>
		<pose>Unspecified</pose>
		<truncated>0</truncated>
		<difficult>0</difficult>
		<bndbox>
			<xmin>377</xmin>
			<ymin>286</ymin>
			<xmax>446</xmax>
			<ymax>357</ymax>
		</bndbox>
	</object>
	<object>
		<name>Phase1_panel_screw_missing</name>
		<pose>Unspecified</pose>
		<truncated>0</truncated>
		<difficult>0</difficult>
		<bndbox>
			<xmin>229</xmin>
			<ymin>199</ymin>
			<xmax>305</xmax>
			<ymax>256</ymax>
		</bndbox>
	</object>
	<object>
		<name>Phase1_panel_screw_missing</name>
		<pose>Unspecified</pose>
		<truncated>0</truncated>
		<difficult>0</difficult>
		<bndbox>
			<xmin>372</xmin>
			<ymin>204</ymin>
			<xmax>444</xmax>
			<ymax>256</ymax>
		</bndbox>
	</object>
</annotation>
